cell_command/__init__.py
cell_command-0.0.0.dist-info/LICENSE
cell_command-0.0.0.dist-info/METADATA
cell_command-0.0.0.dist-info/WHEEL
cell_command-0.0.0.dist-info/top_level.txt
cell_command-0.0.0.dist-info/RECORD
